{
"type": "FeatureCollection",
"features": [
{
  "type": "Feature",
  "id": "node/10939567581",
  "properties": {
    "access": "yes",
    "addr:country": "PT",
    "amenity": "charging_station",
    "capacity": "1",
    "fee": "no",
    "maxstay": "unlimited",
    "motorcar": "yes",
    "no:network": "yes",
    "payment:app": "no",
    "payment:cards": "no",
    "payment:membership_card": "no",
    "socket:cee_blue": "2",
    "socket:cee_blue:current": "16",
    "socket:cee_blue:output": "3.7 kW",
    "socket:cee_blue:voltage": "230",
    "id": "node/10939567581"
  },
  "geometry": {
    "type": "Point",
    "coordinates": [
      -9.1579046,
      39.3581126
    ]
  }
},
{
  "type": "Feature",
  "id": "node/11866861969",
  "properties": {
    "access": "yes",
    "amenity": "charging_station",
    "bicycle": "yes",
    "brand": "Spelsberg",
    "capacity": "4",
    "fee": "no",
    "image": "https://www.spelsberg.de/media/_processed_/9/4/csm_PHO_ANW_AKF-Spelsberg-BCS-Gl-rtalsperre-0083__SALL__AIN__V1_c29bb60636.jpg",
    "motorcar": "no",
    "name": "[BCS] Floema teste",
    "payment:app": "no",
    "payment:cards": "no",
    "payment:membership_card": "no",
    "socket:bosch_3pin": "1",
    "socket:schuko": "2",
    "socket:shimano_steps_5pin": "1",
    "id": "node/11866861969"
  },
  "geometry": {
    "type": "Point",
    "coordinates": [
      -8.4646089,
      40.1100609
    ]
  }
},
{
  "type": "Feature",
  "id": "node/12288652504",
  "properties": {
    "access": "permissive",
    "amenity": "bicycle_parking;bicycle_repair_station",
    "bicycle": "yes",
    "bicycle_parking": "stands",
    "capacity": "11;4",
    "cargo_bike": "yes",
    "covered": "yes",
    "fee": "no",
    "man_made": "charge_point",
    "motorcar": "no",
    "id": "node/12288652504"
  },
  "geometry": {
    "type": "Point",
    "coordinates": [
      -8.4081769,
      40.1945523
    ]
  }
}
]
}
